hypothesis_rdkit/__init__.py
hypothesis_rdkit/files.py
hypothesis_rdkit/fragment.py
hypothesis_rdkit/hook.py
hypothesis_rdkit/storage.py
hypothesis_rdkit/strategy.py
hypothesis_rdkit/util.py
hypothesis_rdkit/version.py
hypothesis_rdkit/polyfills/__init__.py
hypothesis_rdkit/polyfills/block_logs.py
hypothesis_rdkit/polyfills/files.py
hypothesis_rdkit/polyfills/version.py
hypothesis_rdkit/resources/fragments_100000.pkl.gz
hypothesis_rdkit/resources/fragments_100000.smi
hypothesis_rdkit/resources/fragments_30000.pkl.gz
hypothesis_rdkit/resources/fragments_30000.smi
hypothesis_rdkit/resources/fragments_365069.pkl.gz
hypothesis_rdkit/resources/fragments_365069.smi
hypothesis_rdkit-0.6.1.dist-info/LICENSE
hypothesis_rdkit-0.6.1.dist-info/METADATA
hypothesis_rdkit-0.6.1.dist-info/WHEEL
hypothesis_rdkit-0.6.1.dist-info/entry_points.txt
hypothesis_rdkit-0.6.1.dist-info/top_level.txt
hypothesis_rdkit-0.6.1.dist-info/RECORD
