Metadata-Version: 2.1
Name: hypothesis-rdkit
Version: 0.6.1
Summary: Hypothesis strategies for RDKit
Home-page: https://github.com/shirte/hypothesis-rdkit
Maintainer: Steffen Hirte
Maintainer-email: shirte@users.noreply.github.com
License: MIT
Classifier: Programming Language :: Python
Classifier: Programming Language :: Python :: 3
Classifier: Topic :: Software Development :: Libraries :: Python Modules
Classifier: Topic :: Software Development :: Testing
Classifier: Topic :: Scientific/Engineering :: Chemistry
Classifier: Framework :: Hypothesis
Classifier: License :: OSI Approved :: MIT License
License-File: LICENSE
Requires-Dist: hypothesis
Requires-Dist: numpy
Requires-Dist: tqdm
Requires-Dist: platformdirs
Requires-Dist: rdkit >=2022.3.3
Requires-Dist: importlib-metadata >=4.6 ; python_version < "3.10"
Requires-Dist: importlib-resources >=5 ; python_version < "3.9"
Provides-Extra: dev
Requires-Dist: black ; extra == 'dev'
Requires-Dist: isort ; extra == 'dev'
Provides-Extra: test
Requires-Dist: pytest ; extra == 'test'
Requires-Dist: pytest-cov ; extra == 'test'
Requires-Dist: pytest-watch ; extra == 'test'
